tinycalltrace/__init__.py
tinycalltrace-1.0.2.dist-info/DESCRIPTION.rst
tinycalltrace-1.0.2.dist-info/LICENSE.txt
tinycalltrace-1.0.2.dist-info/METADATA
tinycalltrace-1.0.2.dist-info/RECORD
tinycalltrace-1.0.2.dist-info/WHEEL
tinycalltrace-1.0.2.dist-info/metadata.json
tinycalltrace-1.0.2.dist-info/top_level.txt
