Metadata-Version: 2.0
Name: tinycalltrace
Version: 1.0.2
Summary: Simple call tree graph generator suitable for viewing with vim fold
Home-page: https://github.com/nozzy123nozzy/tinycalltrace
Author: Takahide Nojima
Author-email: nozzy123nozzy@gmail.com
License: MIT
Keywords: call tree tracer vim fold
Platform: UNKNOWN
Classifier: Operating System :: Unix
Classifier: Intended Audience :: Developers
Classifier: License :: OSI Approved :: MIT License
Classifier: Topic :: Software Development :: Debuggers
Classifier: Programming Language :: Python :: 3
Requires-Python: >3
